{
  "Name": "EBodyPartName",
  "Description": " ",
  "Variables": [
    {
      "Name": "BPart_None",
      "Value": "0",
      "Description": " "
    },
    {
      "Name": "BPart_HeadPart",
      "Value": "1",
      "Description": " "
    },
    {
      "Name": "BPart_LeftLowerArm",
      "Value": "2",
      "Description": " "
    },
    {
      "Name": "BPart_LeftUpperArm",
      "Value": "3",
      "Description": " "
    },
    {
      "Name": "BPart_LeftThigh",
      "Value": "4",
      "Description": " "
    },
    {
      "Name": "BPart_LeftShank",
      "Value": "5",
      "Description": " "
    },
    {
      "Name": "BPart_RightLowerArm",
      "Value": "6",
      "Description": " "
    },
    {
      "Name": "BPart_RightUpperArm",
      "Value": "7",
      "Description": " "
    },
    {
      "Name": "BPart_RightThigh",
      "Value": "8",
      "Description": " "
    },
    {
      "Name": "BPart_RightShank",
      "Value": "9",
      "Description": " "
    },
    {
      "Name": "Max",
      "Value": "10",
      "Description": " "
    }
  ]
}