{
  "Name": "EBuildingActionType",
  "Description": " ",
  "Variables": [
    {
      "Name": "EBA_PreBuild",
      "Value": "0",
      "Description": " "
    },
    {
      "Name": "EBA_BuildAtScreenPos",
      "Value": "1",
      "Description": " "
    },
    {
      "Name": "EBA_DoubleClickBuild",
      "Value": "2",
      "Description": " "
    },
    {
      "Name": "EBA_CustomEventBuild",
      "Value": "3",
      "Description": " "
    },
    {
      "Name": "EBA_INTERNAL_SERVER_CHECK_TYPE",
      "Value": "99",
      "Description": " "
    },
    {
      "Name": "EBA_Max",
      "Value": "100",
      "Description": " "
    }
  ]
}