{
  "Name": "ECNP_Operation_Type",
  "Description": " ",
  "Variables": [
    {
      "Name": "None",
      "Value": "1",
      "Description": " "
    },
    {
      "Name": "OP_Place",
      "Value": "2",
      "Description": " "
    },
    {
      "Name": "OP_StartConstructBlueprint",
      "Value": "3",
      "Description": " "
    },
    {
      "Name": "OP_PlaceConstructBlueprint",
      "Value": "4",
      "Description": " "
    },
    {
      "Name": "OP_ConfirmEdit",
      "Value": "5",
      "Description": " "
    },
    {
      "Name": "OP_ConfirmBatch",
      "Value": "6",
      "Description": " "
    },
    {
      "Name": "OP_RequestEmpty",
      "Value": "7",
      "Description": " "
    },
    {
      "Name": "OP_Max",
      "Value": "8",
      "Description": " "
    }
  ]
}