{
  "Name": "EEscapeAttachmentSlotType",
  "Description": " ",
  "Variables": [
    {
      "Name": "None",
      "Value": "0",
      "Description": " "
    },
    {
      "Name": "GunPoint",
      "Value": "1",
      "Description": " "
    },
    {
      "Name": "Grip",
      "Value": "2",
      "Description": " "
    },
    {
      "Name": "Magazine",
      "Value": "3",
      "Description": " "
    },
    {
      "Name": "Gunstock",
      "Value": "4",
      "Description": " "
    },
    {
      "Name": "OpticalSight",
      "Value": "5",
      "Description": " "
    },
    {
      "Name": "AngledOpticalSight",
      "Value": "6",
      "Description": " "
    },
    {
      "Name": "ArmorSlot1",
      "Value": "7",
      "Description": " "
    },
    {
      "Name": "ArmorSlot2",
      "Value": "8",
      "Description": " "
    },
    {
      "Name": "ArmorSlot3",
      "Value": "9",
      "Description": " "
    },
    {
      "Name": "ArmorSlot4",
      "Value": "10",
      "Description": " "
    },
    {
      "Name": "ArmorSlot5",
      "Value": "11",
      "Description": " "
    }
  ]
}