{
  "Name": "EExtraAnimDataType_MoveAimExtend",
  "Description": " ",
  "Variables": [
    {
      "Name": "MoveAimExtend_IdleAim",
      "Value": "0",
      "Description": " "
    },
    {
      "Name": "MoveAimExtend_Idle",
      "Value": "1",
      "Description": " "
    },
    {
      "Name": "MoveAimExtend_IdleTurn",
      "Value": "2",
      "Description": " "
    },
    {
      "Name": "MoveAimExtend_Run",
      "Value": "3",
      "Description": " "
    },
    {
      "Name": "MoveAimExtend_Sprint",
      "Value": "4",
      "Description": " "
    },
    {
      "Name": "MoveAimExtend_SprintLean",
      "Value": "5",
      "Description": " "
    },
    {
      "Name": "MoveAimExtend_IdleToRun",
      "Value": "6",
      "Description": " "
    },
    {
      "Name": "MoveAimExtend_IdleToSprint",
      "Value": "7",
      "Description": " "
    },
    {
      "Name": "MoveAimExtend_RunToIdle_Left",
      "Value": "8",
      "Description": " "
    },
    {
      "Name": "MoveAimExtend_RunToIdle_Right",
      "Value": "9",
      "Description": " "
    },
    {
      "Name": "MoveAimExtend_SprintToIdle_Left",
      "Value": "10",
      "Description": " "
    },
    {
      "Name": "MoveAimExtend_SprintToIdle_Right",
      "Value": "11",
      "Description": " "
    },
    {
      "Name": "MoveAimExtend_SprintCrushDoor",
      "Value": "12",
      "Description": " "
    }
  ]
}