{
  "Name": "EFinderShape",
  "Description": " ",
  "Variables": [
    {
      "Name": "Line",
      "Value": "0",
      "Description": " "
    },
    {
      "Name": "Box",
      "Value": "1",
      "Description": " "
    },
    {
      "Name": "Sphere",
      "Value": "2",
      "Description": " "
    },
    {
      "Name": "Capsule",
      "Value": "3",
      "Description": " "
    },
    {
      "Name": "Cone",
      "Value": "4",
      "Description": " "
    },
    {
      "Name": "Fan",
      "Value": "5",
      "Description": " "
    },
    {
      "Name": "Complex",
      "Value": "6",
      "Description": " "
    }
  ]
}