{
  "Name": "EMechanicalArmType",
  "Description": " ",
  "Variables": [
    {
      "Name": "MAT_Default",
      "Value": "0",
      "Description": " "
    },
    {
      "Name": "MAT_FrontUpperArm",
      "Value": "1",
      "Description": " "
    },
    {
      "Name": "MAT_LeftHindLeg",
      "Value": "2",
      "Description": " "
    },
    {
      "Name": "MAT_RightHindLeg",
      "Value": "3",
      "Description": " "
    },
    {
      "Name": "MAT_FrontForeArm",
      "Value": "4",
      "Description": " "
    },
    {
      "Name": "MAT_Bucket",
      "Value": "5",
      "Description": " "
    },
    {
      "Name": "MAT_LeftBehindClaw",
      "Value": "6",
      "Description": " "
    },
    {
      "Name": "MAT_RightBehindClaw",
      "Value": "7",
      "Description": " "
    },
    {
      "Name": "MAT_Base",
      "Value": "8",
      "Description": " "
    },
    {
      "Name": "MAT_LeftFrontLeg",
      "Value": "9",
      "Description": " "
    },
    {
      "Name": "MAT_RightFrontLeg",
      "Value": "10",
      "Description": " "
    },
    {
      "Name": "MAT_TotalNum",
      "Value": "11",
      "Description": " "
    }
  ]
}