{
  "Name": "EUniversalTaskTableParamType",
  "Description": " ",
  "Variables": [
    {
      "Name": "ETT_ParamNone",
      "Value": "0",
      "Description": " "
    },
    {
      "Name": "ETT_IntParamFirst",
      "Value": "1",
      "Description": " "
    },
    {
      "Name": "ETT_IntParamSecond",
      "Value": "2",
      "Description": " "
    },
    {
      "Name": "ETT_IntParamThird",
      "Value": "3",
      "Description": " "
    },
    {
      "Name": "ETT_IntParamFourth",
      "Value": "4",
      "Description": " "
    },
    {
      "Name": "ETT_IntParamFiveth",
      "Value": "5",
      "Description": " "
    },
    {
      "Name": "ETT_IntParamSixth",
      "Value": "6",
      "Description": " "
    },
    {
      "Name": "ETT_StrParamFirst",
      "Value": "20",
      "Description": " "
    },
    {
      "Name": "ETT_StrParamSecond",
      "Value": "21",
      "Description": " "
    },
    {
      "Name": "ETT_StrParamThird",
      "Value": "22",
      "Description": " "
    },
    {
      "Name": "ETT_StrParamFourth",
      "Value": "23",
      "Description": " "
    },
    {
      "Name": "ETT_StrParamFiveth",
      "Value": "24",
      "Description": " "
    },
    {
      "Name": "ETT_StrParamSixth",
      "Value": "25",
      "Description": " "
    }
  ]
}