{
  "Name": "FCurveEdTab",
  "Description": "",
  "Variables": [
    {
      "Name": "TabName",
      "Type": "FString",
      "Description": "",
      "Redirect": ""
    },
    {
      "Name": "Curves",
      "Type": "TArray < struct FCurveEdEntry >",
      "Description": "",
      "Redirect": ""
    },
    {
      "Name": "ViewStartInput",
      "Type": "float",
      "Description": "",
      "Redirect": ""
    },
    {
      "Name": "ViewEndInput",
      "Type": "float",
      "Description": "",
      "Redirect": ""
    },
    {
      "Name": "ViewStartOutput",
      "Type": "float",
      "Description": "",
      "Redirect": ""
    },
    {
      "Name": "ViewEndOutput",
      "Type": "float",
      "Description": "",
      "Redirect": ""
    }
  ]
}