{
  "Name": "FCurveEdEntry",
  "Description": "",
  "Variables": [
    {
      "Name": "CurveObject",
      "Type": "UObject *",
      "Description": "",
      "Redirect": ""
    },
    {
      "Name": "CurveColor",
      "Type": "FColor",
      "Description": "",
      "Redirect": ""
    },
    {
      "Name": "CurveName",
      "Type": "FString",
      "Description": "",
      "Redirect": ""
    },
    {
      "Name": "bHideCurve",
      "Type": "int32",
      "Description": "",
      "Redirect": ""
    },
    {
      "Name": "bColorCurve",
      "Type": "int32",
      "Description": "",
      "Redirect": ""
    },
    {
      "Name": "bFloatingPointColorCurve",
      "Type": "int32",
      "Description": "",
      "Redirect": ""
    },
    {
      "Name": "bClamp",
      "Type": "int32",
      "Description": "",
      "Redirect": ""
    },
    {
      "Name": "ClampLow",
      "Type": "float",
      "Description": "",
      "Redirect": ""
    },
    {
      "Name": "ClampHigh",
      "Type": "float",
      "Description": "",
      "Redirect": ""
    }
  ]
}