{
  "Name": "FMeshSectionInfo",
  "Description": "Per-section settings.",
  "Variables": [
    {
      "Name": "MaterialIndex",
      "Type": "int32",
      "Description": "Index in to the Materials array on UStaticMesh.",
      "Redirect": ""
    },
    {
      "Name": "bEnableCollision",
      "Type": "bool",
      "Description": "If true, collision is enabled for this section.",
      "Redirect": ""
    },
    {
      "Name": "bCastShadow",
      "Type": "bool",
      "Description": "If true, this section will cast shadows.",
      "Redirect": ""
    }
  ]
}