{
  "Name": "FRandomPlayerSequenceEntry",
  "Description": "The random player node holds a list of sequences and parameter ranges which will be played continuously\n   In a random order. If shuffle mode is enabled then each entry will be played once before repeating any",
  "Variables": [
    {
      "Name": "Sequence",
      "Type": "UAnimSequenceBase *",
      "Description": "Sequence to play when this entry is picked",
      "Redirect": ""
    },
    {
      "Name": "ChanceToPlay",
      "Type": "float",
      "Description": "When not in shuffle mode, this is the chance this entry will play (normalized against all other sample chances)",
      "Redirect": ""
    },
    {
      "Name": "MinLoopCount",
      "Type": "int32",
      "Description": "Minimum number of times this entry will loop before ending",
      "Redirect": ""
    },
    {
      "Name": "MaxLoopCount",
      "Type": "int32",
      "Description": "Maximum number of times this entry will loop before ending",
      "Redirect": ""
    },
    {
      "Name": "MinPlayRate",
      "Type": "float",
      "Description": "Minimum playrate for this entry",
      "Redirect": ""
    },
    {
      "Name": "MaxPlayRate",
      "Type": "float",
      "Description": "Maximum playrate for this entry",
      "Redirect": ""
    },
    {
      "Name": "BlendIn",
      "Type": "FAlphaBlend",
      "Description": "Blending properties used when this entry is blending in ontop of another entry",
      "Redirect": ""
    }
  ]
}