{
  "Name": "FTOD_Moon",
  "Description": "",
  "Variables": [
    {
      "Name": "MoonColor",
      "Type": "FLinearColor",
      "Description": "",
      "Redirect": ""
    },
    {
      "Name": "MoonHaloColor",
      "Type": "FLinearColor",
      "Description": "",
      "Redirect": ""
    },
    {
      "Name": "MoonHaloSmooth",
      "Type": "float",
      "Description": "",
      "Redirect": ""
    },
    {
      "Name": "MoonRadius_Halo",
      "Type": "float",
      "Description": "",
      "Redirect": ""
    },
    {
      "Name": "MoonRimLightIntensity",
      "Type": "float",
      "Description": "",
      "Redirect": ""
    },
    {
      "Name": "MoonSize",
      "Type": "float",
      "Description": "",
      "Redirect": ""
    },
    {
      "Name": "MoonDis_DEPRECATED",
      "Type": "float",
      "Description": "",
      "Redirect": ""
    },
    {
      "Name": "MoonScale_DEPRECATED",
      "Type": "float",
      "Description": "",
      "Redirect": ""
    },
    {
      "Name": "UseMoon_DEPRECATED",
      "Type": "bool",
      "Description": "",
      "Redirect": ""
    }
  ]
}