{
  "Name": "UGridVisibilityCaptureComponent",
  "Description": "",
  "Variables": [
    {
      "Name": "FOVAngle",
      "Type": "float",
      "Description": "Camera field of view (in degrees).",
      "Redirect": ""
    },
    {
      "Name": "CaptureViewSize",
      "Type": "FIntPoint",
      "Description": "",
      "Redirect": ""
    },
    {
      "Name": "NearClipPlane",
      "Type": "float",
      "Description": "",
      "Redirect": ""
    },
    {
      "Name": "GridMesh",
      "Type": "UStaticMesh *",
      "Description": "",
      "Redirect": ""
    },
    {
      "Name": "GridMeshSizeScale",
      "Type": "FVector",
      "Description": "",
      "Redirect": ""
    },
    {
      "Name": "GridMeshLocationOffset",
      "Type": "FVector",
      "Description": "",
      "Redirect": ""
    },
    {
      "Name": "bForceLowestLOD",
      "Type": "uint32",
      "Description": "",
      "Redirect": ""
    },
    {
      "Name": "bHiddenFoliage",
      "Type": "uint32",
      "Description": "",
      "Redirect": ""
    },
    {
      "Name": "OcclusionDepthDiffThreshold",
      "Type": "float",
      "Description": "",
      "Redirect": ""
    },
    {
      "Name": "bShouldRenderGridMeshInMainPass",
      "Type": "uint32",
      "Description": "",
      "Redirect": ""
    },
    {
      "Name": "MaxNumProcessWaitingResultCmdsPerFrame",
      "Type": "int32",
      "Description": "",
      "Redirect": ""
    },
    {
      "Name": "MaxNumProcessWaitingCalculateCmdsPerFrame",
      "Type": "int32",
      "Description": "",
      "Redirect": ""
    },
    {
      "Name": "GridSize",
      "Type": "FIntPoint",
      "Description": "",
      "Redirect": ""
    },
    {
      "Name": "RenderTargetToCreateRenderer",
      "Type": "UTextureRenderTarget2D *",
      "Description": "",
      "Redirect": ""
    },
    {
      "Name": "GridMeshComp",
      "Type": "UInstancedStaticMeshComponent *",
      "Description": "",
      "Redirect": ""
    }
  ],
  "Functions": [
    {
      "Name": "InitGridIDVisibilityCalculation",
      "Description": "",
      "Params": [
        {
          "Name": "InGridLocations",
          "Type": "TArray < FVector > &",
          "Description": "",
          "Redirect": ""
        }
      ],
      "Return": [
        {
          "Name": "",
          "Type": "void ",
          "Description": "",
          "Redirect": ""
        }
      ]
    },
    {
      "Name": "CalculateGridIDVisibility",
      "Description": "",
      "Params": [
        {
          "Name": "GridID",
          "Type": "int32 ",
          "Description": "",
          "Redirect": ""
        },
        {
          "Name": "CameraLocations",
          "Type": "TArray < FGridVisibilityCameraInfo > & ",
          "Description": "",
          "Redirect": ""
        },
        {
          "Name": "PotentialGrids",
          "Type": "TArray < int32 > &",
          "Description": "",
          "Redirect": ""
        }
      ],
      "Return": [
        {
          "Name": "",
          "Type": "void ",
          "Description": "",
          "Redirect": ""
        }
      ]
    },
    {
      "Name": "FinishGridIDVisibilityCalculation",
      "Description": "",
      "Params": null,
      "Return": [
        {
          "Name": "",
          "Type": "void",
          "Description": "",
          "Redirect": ""
        }
      ]
    }
  ],
  "Parents": [
    "USceneComponent"
  ],
  "Event": null,
  "Delegate": null,
  "Language": "cpp"
}