{
  "Name": "USceneCaptureComponent",
  "Description": "",
  "Variables": [
    {
      "Name": "PrimitiveRenderMode",
      "Type": "ESceneCapturePrimitiveRenderMode",
      "Description": "Controls what primitives get rendered into the scene capture.",
      "Redirect": ""
    },
    {
      "Name": "HiddenComponents",
      "Type": "TArray < TWeakObjectPtr < UPrimitiveComponent > >",
      "Description": "The components won't rendered by current component.",
      "Redirect": ""
    },
    {
      "Name": "HiddenActors",
      "Type": "TArray < AActor * >",
      "Description": "The actors to hide in the scene capture.",
      "Redirect": ""
    },
    {
      "Name": "ShowOnlyComponents",
      "Type": "TArray < TWeakObjectPtr < UPrimitiveComponent > >",
      "Description": "The only components to be rendered by this scene capture, if PrimitiveRenderMode is set to UseShowOnlyList.",
      "Redirect": ""
    },
    {
      "Name": "bShowAttachedActor",
      "Type": "bool",
      "Description": "",
      "Redirect": ""
    },
    {
      "Name": "ShowOnlyActors",
      "Type": "TArray < AActor * >",
      "Description": "The only actors to be rendered by this scene capture, if PrimitiveRenderMode is set to UseShowOnlyList.",
      "Redirect": ""
    },
    {
      "Name": "bCaptureEveryFrame",
      "Type": "bool",
      "Description": "Whether to update the capture's contents every frame.  If disabled, the component will render once on load and then only when moved.",
      "Redirect": ""
    },
    {
      "Name": "bCaptureOnMovement",
      "Type": "bool",
      "Description": "Whether to update the capture's contents on movement.  Disable if you are going to capture manually from blueprint.",
      "Redirect": ""
    },
    {
      "Name": "bAlwaysPersistRenderingState",
      "Type": "bool",
      "Description": "Whether to persist the rendering state even if bCaptureEveryFrame==false.  This allows velocities for Motion Blur and Temporal AA to be computed.",
      "Redirect": ""
    },
    {
      "Name": "LODDistanceFactor",
      "Type": "float",
      "Description": "Scales the distance used by LOD. Set to values greater than 1 to cause the scene capture to use lower LODs than the main view to speed up the scene capture pass.",
      "Redirect": ""
    },
    {
      "Name": "MaxViewDistanceOverride",
      "Type": "float",
      "Description": "if > 0, sets a maximum render distance override.  Can be used to cull distant objects from a reflection if the reflecting plane is in an enclosed area like a hallway or room",
      "Redirect": ""
    },
    {
      "Name": "CaptureSortPriority",
      "Type": "int32",
      "Description": "Capture priority within the frame to sort scene capture on GPU to resolve interdependencies between multiple capture components. Highest come first.",
      "Redirect": ""
    },
    {
      "Name": "ShowFlagSettings",
      "Type": "TArray < struct FEngineShowFlagsSetting >",
      "Description": "ShowFlags for the SceneCapture's ViewFamily, to control rendering settings for this view. Hidden but accessible through details customization",
      "Redirect": ""
    },
    {
      "Name": "LightingChannels",
      "Type": "FLightingChannels",
      "Description": "",
      "Redirect": ""
    },
    {
      "Name": "bUseLightingChannels",
      "Type": "bool",
      "Description": "",
      "Redirect": ""
    }
  ],
  "Functions": [
    {
      "Name": "HideComponent",
      "Description": "Adds the component to our list of hidden components.",
      "Params": [
        {
          "Name": "InComponent",
          "Type": "UPrimitiveComponent *",
          "Description": "",
          "Redirect": ""
        }
      ],
      "Return": [
        {
          "Name": "",
          "Type": "void ",
          "Description": "",
          "Redirect": ""
        }
      ]
    },
    {
      "Name": "HideActorComponents",
      "Description": "Adds all primitive components in the actor to our list of hidden components.",
      "Params": [
        {
          "Name": "InActor",
          "Type": "AActor *",
          "Description": "",
          "Redirect": ""
        }
      ],
      "Return": [
        {
          "Name": "",
          "Type": "void ",
          "Description": "",
          "Redirect": ""
        }
      ]
    },
    {
      "Name": "ShowOnlyComponent",
      "Description": "Adds the component to our list of show-only components.",
      "Params": [
        {
          "Name": "InComponent",
          "Type": "UPrimitiveComponent *",
          "Description": "",
          "Redirect": ""
        }
      ],
      "Return": [
        {
          "Name": "",
          "Type": "void ",
          "Description": "",
          "Redirect": ""
        }
      ]
    },
    {
      "Name": "ShowOnlyActorComponents",
      "Description": "Adds all primitive components in the actor to our list of show-only components.",
      "Params": [
        {
          "Name": "InActor",
          "Type": "AActor *",
          "Description": "",
          "Redirect": ""
        }
      ],
      "Return": [
        {
          "Name": "",
          "Type": "void ",
          "Description": "",
          "Redirect": ""
        }
      ]
    },
    {
      "Name": "RemoveShowOnlyComponent",
      "Description": "Removes a component from the Show Only list.",
      "Params": [
        {
          "Name": "InComponent",
          "Type": "UPrimitiveComponent *",
          "Description": "",
          "Redirect": ""
        }
      ],
      "Return": [
        {
          "Name": "",
          "Type": "void ",
          "Description": "",
          "Redirect": ""
        }
      ]
    },
    {
      "Name": "RemoveShowOnlyActorComponents",
      "Description": "Removes a actor's components from the Show Only list.",
      "Params": [
        {
          "Name": "InActor",
          "Type": "AActor *",
          "Description": "",
          "Redirect": ""
        }
      ],
      "Return": [
        {
          "Name": "",
          "Type": "void ",
          "Description": "",
          "Redirect": ""
        }
      ]
    },
    {
      "Name": "ClearShowOnlyComponents",
      "Description": "Clears the Show Only list.",
      "Params": null,
      "Return": [
        {
          "Name": "",
          "Type": "void",
          "Description": "",
          "Redirect": ""
        }
      ]
    },
    {
      "Name": "ClearHiddenComponents",
      "Description": "Clears the hidden list.",
      "Params": null,
      "Return": [
        {
          "Name": "",
          "Type": "void",
          "Description": "",
          "Redirect": ""
        }
      ]
    },
    {
      "Name": "SetCaptureSortPriority",
      "Description": "Changes the value of TranslucentSortPriority.",
      "Params": [
        {
          "Name": "NewCaptureSortPriority",
          "Type": "int32",
          "Description": "",
          "Redirect": ""
        }
      ],
      "Return": [
        {
          "Name": "",
          "Type": "void ",
          "Description": "",
          "Redirect": ""
        }
      ]
    }
  ],
  "Parents": [
    "USceneComponent"
  ],
  "Event": null,
  "Delegate": null,
  "Language": "cpp"
}