{
  "Name": "USoundNodeGroupControl",
  "Description": "Plays different sounds depending on the number of active sounds\n  Any time a new sound is played, the first group that has an available slot will be chosen",
  "Variables": [
    {
      "Name": "GroupSizes",
      "Type": "TArray < int32 >",
      "Description": "How many active sounds are allowed for each group",
      "Redirect": ""
    }
  ],
  "Functions": null,
  "Parents": [
    "USoundNode"
  ],
  "Event": null,
  "Delegate": null,
  "Language": "cpp"
}